[{"ID":1510101,"Name":1510100,"Preview":1,"Position":1,"SymbolQuality":10,"ResMat":[1,10,5],"Consume":[500001,100],"ResQuality":[1,20],"Reset":[],"Weight":250},{"ID":1510102,"Name":1510100,"Preview":0,"Position":1,"SymbolQuality":20,"ResMat":[1,20,5],"Consume":[500001,500],"ResQuality":[1,30],"Reset":[],"Weight":250},{"ID":1510103,"Name":1510100,"Preview":0,"Position":1,"SymbolQuality":30,"ResMat":[1,30,5],"Consume":[500001,2500],"ResQuality":[1,40],"Reset":[],"Weight":250},{"ID":1510104,"Name":1510100,"Preview":0,"Position":1,"SymbolQuality":40,"ResMat":[1,40,5],"Consume":[500001,12500],"ResQuality":[1,50],"Reset":[],"Weight":250},{"ID":1510105,"Name":1510100,"Preview":0,"Position":1,"SymbolQuality":50,"ResMat":[1,50,5],"Consume":[500001,50000],"ResQuality":[1,60],"Reset":[502201,1],"Weight":250},{"ID":1510106,"Name":1510100,"Preview":0,"Position":1,"SymbolQuality":60,"ResMat":[1,60,5],"Consume":[500001,25000],"ResQuality":[1,70],"Reset":[502201,2],"Weight":250},{"ID":1510107,"Name":1510100,"Preview":0,"Position":1,"SymbolQuality":70,"ResMat":[1,70,2],"Consume":[500001,125000],"ResQuality":[1,70],"Reset":[502201,4],"Weight":250},{"ID":1510201,"Name":1510200,"Preview":0,"Position":1,"SymbolQuality":10,"ResMat":[1,10,5],"Consume":[500001,100],"ResQuality":[1,20],"Reset":[0],"Weight":0},{"ID":1510202,"Name":1510200,"Preview":0,"Position":1,"SymbolQuality":20,"ResMat":[1,20,5],"Consume":[500001,500],"ResQuality":[1,30],"Reset":[0],"Weight":0},{"ID":1510203,"Name":1510200,"Preview":1,"Position":1,"SymbolQuality":30,"ResMat":[1,30,5],"Consume":[500001,2500],"ResQuality":[1,40],"Reset":[0],"Weight":150},{"ID":1510204,"Name":1510200,"Preview":0,"Position":1,"SymbolQuality":40,"ResMat":[1,40,5],"Consume":[500001,12500],"ResQuality":[1,50],"Reset":[0],"Weight":150},{"ID":1510205,"Name":1510200,"Preview":0,"Position":1,"SymbolQuality":50,"ResMat":[1,50,5],"Consume":[500001,50000],"ResQuality":[1,60],"Reset":[502201,1],"Weight":150},{"ID":1510206,"Name":1510200,"Preview":0,"Position":1,"SymbolQuality":60,"ResMat":[1,60,5],"Consume":[500001,25000],"ResQuality":[1,70],"Reset":[502201,2],"Weight":150},{"ID":1510207,"Name":1510200,"Preview":0,"Position":1,"SymbolQuality":70,"ResMat":[1,70,2],"Consume":[500001,125000],"ResQuality":[1,70],"Reset":[502201,4],"Weight":150},{"ID":1510301,"Name":1510300,"Preview":0,"Position":1,"SymbolQuality":10,"ResMat":[1,10,5],"Consume":[500001,100],"ResQuality":[1,20],"Reset":[0],"Weight":0},{"ID":1510302,"Name":1510300,"Preview":0,"Position":1,"SymbolQuality":20,"ResMat":[1,20,5],"Consume":[500001,500],"ResQuality":[1,30],"Reset":[0],"Weight":0},{"ID":1510303,"Name":1510300,"Preview":1,"Position":1,"SymbolQuality":30,"ResMat":[1,30,5],"Consume":[500001,2500],"ResQuality":[1,40],"Reset":[0],"Weight":250},{"ID":1510304,"Name":1510300,"Preview":0,"Position":1,"SymbolQuality":40,"ResMat":[1,40,5],"Consume":[500001,12500],"ResQuality":[1,50],"Reset":[0],"Weight":250},{"ID":1510305,"Name":1510300,"Preview":0,"Position":1,"SymbolQuality":50,"ResMat":[1,50,5],"Consume":[500001,50000],"ResQuality":[1,60],"Reset":[502201,1],"Weight":250},{"ID":1510306,"Name":1510300,"Preview":0,"Position":1,"SymbolQuality":60,"ResMat":[1,60,5],"Consume":[500001,25000],"ResQuality":[1,70],"Reset":[502201,2],"Weight":250},{"ID":1510307,"Name":1510300,"Preview":0,"Position":1,"SymbolQuality":70,"ResMat":[1,70,2],"Consume":[500001,125000],"ResQuality":[1,70],"Reset":[502201,4],"Weight":250},{"ID":1510401,"Name":1510400,"Preview":1,"Position":1,"SymbolQuality":10,"ResMat":[1,10,5],"Consume":[500001,100],"ResQuality":[1,20],"Reset":[0],"Weight":50},{"ID":1510402,"Name":1510400,"Preview":0,"Position":1,"SymbolQuality":20,"ResMat":[1,20,5],"Consume":[500001,500],"ResQuality":[1,30],"Reset":[0],"Weight":50},{"ID":1510403,"Name":1510400,"Preview":0,"Position":1,"SymbolQuality":30,"ResMat":[1,30,5],"Consume":[500001,2500],"ResQuality":[1,40],"Reset":[0],"Weight":50},{"ID":1510404,"Name":1510400,"Preview":0,"Position":1,"SymbolQuality":40,"ResMat":[1,40,5],"Consume":[500001,12500],"ResQuality":[1,50],"Reset":[0],"Weight":50},{"ID":1510405,"Name":1510400,"Preview":0,"Position":1,"SymbolQuality":50,"ResMat":[1,50,5],"Consume":[500001,50000],"ResQuality":[1,60],"Reset":[502201,1],"Weight":50},{"ID":1510406,"Name":1510400,"Preview":0,"Position":1,"SymbolQuality":60,"ResMat":[1,60,5],"Consume":[500001,25000],"ResQuality":[1,70],"Reset":[502201,2],"Weight":50},{"ID":1510407,"Name":1510400,"Preview":0,"Position":1,"SymbolQuality":70,"ResMat":[1,70,2],"Consume":[500001,125000],"ResQuality":[1,70],"Reset":[502201,4],"Weight":50},{"ID":1510501,"Name":1510500,"Preview":0,"Position":1,"SymbolQuality":10,"ResMat":[1,10,5],"Consume":[500001,100],"ResQuality":[1,20],"Reset":[0],"Weight":0},{"ID":1510502,"Name":1510500,"Preview":0,"Position":1,"SymbolQuality":20,"ResMat":[1,20,5],"Consume":[500001,500],"ResQuality":[1,30],"Reset":[0],"Weight":0},{"ID":1510503,"Name":1510500,"Preview":0,"Position":1,"SymbolQuality":30,"ResMat":[1,30,5],"Consume":[500001,2500],"ResQuality":[1,40],"Reset":[0],"Weight":0},{"ID":1510504,"Name":1510500,"Preview":1,"Position":1,"SymbolQuality":40,"ResMat":[1,40,5],"Consume":[500001,12500],"ResQuality":[1,50],"Reset":[0],"Weight":150},{"ID":1510505,"Name":1510500,"Preview":0,"Position":1,"SymbolQuality":50,"ResMat":[1,50,5],"Consume":[500001,50000],"ResQuality":[1,60],"Reset":[502201,1],"Weight":150},{"ID":1510506,"Name":1510500,"Preview":0,"Position":1,"SymbolQuality":60,"ResMat":[1,60,5],"Consume":[500001,25000],"ResQuality":[1,70],"Reset":[502201,2],"Weight":150},{"ID":1510507,"Name":1510500,"Preview":0,"Position":1,"SymbolQuality":70,"ResMat":[1,70,2],"Consume":[500001,125000],"ResQuality":[1,70],"Reset":[502201,4],"Weight":150},{"ID":1510601,"Name":1510600,"Preview":0,"Position":1,"SymbolQuality":10,"ResMat":[1,10,5],"Consume":[500001,100],"ResQuality":[1,20],"Reset":[0],"Weight":0},{"ID":1510602,"Name":1510600,"Preview":0,"Position":1,"SymbolQuality":20,"ResMat":[1,20,5],"Consume":[500001,500],"ResQuality":[1,30],"Reset":[0],"Weight":0},{"ID":1510603,"Name":1510600,"Preview":0,"Position":1,"SymbolQuality":30,"ResMat":[1,30,5],"Consume":[500001,2500],"ResQuality":[1,40],"Reset":[0],"Weight":0},{"ID":1510604,"Name":1510600,"Preview":1,"Position":1,"SymbolQuality":40,"ResMat":[1,40,5],"Consume":[500001,12500],"ResQuality":[1,50],"Reset":[0],"Weight":150},{"ID":1510605,"Name":1510600,"Preview":0,"Position":1,"SymbolQuality":50,"ResMat":[1,50,5],"Consume":[500001,50000],"ResQuality":[1,60],"Reset":[502201,1],"Weight":150},{"ID":1510606,"Name":1510600,"Preview":0,"Position":1,"SymbolQuality":60,"ResMat":[1,60,5],"Consume":[500001,25000],"ResQuality":[1,70],"Reset":[502201,2],"Weight":150},{"ID":1510607,"Name":1510600,"Preview":0,"Position":1,"SymbolQuality":70,"ResMat":[1,70,2],"Consume":[500001,125000],"ResQuality":[1,70],"Reset":[502201,4],"Weight":150},{"ID":1510701,"Name":1510700,"Preview":0,"Position":1,"SymbolQuality":10,"ResMat":[1,10,5],"Consume":[500001,100],"ResQuality":[1,20],"Reset":[0],"Weight":0},{"ID":1510702,"Name":1510700,"Preview":0,"Position":1,"SymbolQuality":20,"ResMat":[1,20,5],"Consume":[500001,500],"ResQuality":[1,30],"Reset":[0],"Weight":0},{"ID":1510703,"Name":1510700,"Preview":0,"Position":1,"SymbolQuality":30,"ResMat":[1,30,5],"Consume":[500001,2500],"ResQuality":[1,40],"Reset":[0],"Weight":0},{"ID":1510704,"Name":1510700,"Preview":1,"Position":1,"SymbolQuality":40,"ResMat":[1,40,5],"Consume":[500001,12500],"ResQuality":[1,50],"Reset":[0],"Weight":50},{"ID":1510705,"Name":1510700,"Preview":0,"Position":1,"SymbolQuality":50,"ResMat":[1,50,5],"Consume":[500001,50000],"ResQuality":[1,60],"Reset":[502201,1],"Weight":50},{"ID":1510706,"Name":1510700,"Preview":0,"Position":1,"SymbolQuality":60,"ResMat":[1,60,5],"Consume":[500001,25000],"ResQuality":[1,70],"Reset":[502201,2],"Weight":50},{"ID":1510707,"Name":1510700,"Preview":0,"Position":1,"SymbolQuality":70,"ResMat":[1,70,2],"Consume":[500001,125000],"ResQuality":[1,70],"Reset":[502201,4],"Weight":50},{"ID":1510801,"Name":1510800,"Preview":0,"Position":1,"SymbolQuality":10,"ResMat":[1,10,5],"Consume":[500001,100],"ResQuality":[1,20],"Reset":[0],"Weight":0},{"ID":1510802,"Name":1510800,"Preview":1,"Position":1,"SymbolQuality":20,"ResMat":[1,20,5],"Consume":[500001,500],"ResQuality":[1,30],"Reset":[0],"Weight":250},{"ID":1510803,"Name":1510800,"Preview":0,"Position":1,"SymbolQuality":30,"ResMat":[1,30,5],"Consume":[500001,2500],"ResQuality":[1,40],"Reset":[0],"Weight":250},{"ID":1510804,"Name":1510800,"Preview":0,"Position":1,"SymbolQuality":40,"ResMat":[1,40,5],"Consume":[500001,12500],"ResQuality":[1,50],"Reset":[0],"Weight":250},{"ID":1510805,"Name":1510800,"Preview":0,"Position":1,"SymbolQuality":50,"ResMat":[1,50,5],"Consume":[500001,50000],"ResQuality":[1,60],"Reset":[502201,1],"Weight":250},{"ID":1510806,"Name":1510800,"Preview":0,"Position":1,"SymbolQuality":60,"ResMat":[1,60,5],"Consume":[500001,25000],"ResQuality":[1,70],"Reset":[502201,2],"Weight":250},{"ID":1510807,"Name":1510800,"Preview":0,"Position":1,"SymbolQuality":70,"ResMat":[1,70,2],"Consume":[500001,125000],"ResQuality":[1,70],"Reset":[502201,4],"Weight":250},{"ID":1510901,"Name":1510900,"Preview":0,"Position":1,"SymbolQuality":10,"ResMat":[1,10,5],"Consume":[500001,100],"ResQuality":[1,20],"Reset":[0],"Weight":0},{"ID":1510902,"Name":1510900,"Preview":1,"Position":1,"SymbolQuality":20,"ResMat":[1,20,5],"Consume":[500001,500],"ResQuality":[1,30],"Reset":[0],"Weight":250},{"ID":1510903,"Name":1510900,"Preview":0,"Position":1,"SymbolQuality":30,"ResMat":[1,30,5],"Consume":[500001,2500],"ResQuality":[1,40],"Reset":[0],"Weight":250},{"ID":1510904,"Name":1510900,"Preview":0,"Position":1,"SymbolQuality":40,"ResMat":[1,40,5],"Consume":[500001,12500],"ResQuality":[1,50],"Reset":[0],"Weight":250},{"ID":1510905,"Name":1510900,"Preview":0,"Position":1,"SymbolQuality":50,"ResMat":[1,50,5],"Consume":[500001,50000],"ResQuality":[1,60],"Reset":[502201,1],"Weight":250},{"ID":1510906,"Name":1510900,"Preview":0,"Position":1,"SymbolQuality":60,"ResMat":[1,60,5],"Consume":[500001,25000],"ResQuality":[1,70],"Reset":[502201,2],"Weight":250},{"ID":1510907,"Name":1510900,"Preview":0,"Position":1,"SymbolQuality":70,"ResMat":[1,70,2],"Consume":[500001,125000],"ResQuality":[1,70],"Reset":[502201,4],"Weight":250},{"ID":1511001,"Name":1511000,"Preview":1,"Position":1,"SymbolQuality":10,"ResMat":[1,10,5],"Consume":[500001,100],"ResQuality":[1,20],"Reset":[0],"Weight":150},{"ID":1511002,"Name":1511000,"Preview":0,"Position":1,"SymbolQuality":20,"ResMat":[1,20,5],"Consume":[500001,500],"ResQuality":[1,30],"Reset":[0],"Weight":150},{"ID":1511003,"Name":1511000,"Preview":0,"Position":1,"SymbolQuality":30,"ResMat":[1,30,5],"Consume":[500001,2500],"ResQuality":[1,40],"Reset":[0],"Weight":150},{"ID":1511004,"Name":1511000,"Preview":0,"Position":1,"SymbolQuality":40,"ResMat":[1,40,5],"Consume":[500001,12500],"ResQuality":[1,50],"Reset":[0],"Weight":150},{"ID":1511005,"Name":1511000,"Preview":0,"Position":1,"SymbolQuality":50,"ResMat":[1,50,5],"Consume":[500001,50000],"ResQuality":[1,60],"Reset":[502201,1],"Weight":150},{"ID":1511006,"Name":1511000,"Preview":0,"Position":1,"SymbolQuality":60,"ResMat":[1,60,5],"Consume":[500001,25000],"ResQuality":[1,70],"Reset":[502201,2],"Weight":150},{"ID":1511007,"Name":1511000,"Preview":0,"Position":1,"SymbolQuality":70,"ResMat":[1,70,2],"Consume":[500001,125000],"ResQuality":[1,70],"Reset":[502201,4],"Weight":150},{"ID":1520101,"Name":1520100,"Preview":1,"Position":2,"SymbolQuality":10,"ResMat":[2,10,5],"Consume":[500001,100],"ResQuality":[2,20],"Reset":[0],"Weight":250},{"ID":1520102,"Name":1520100,"Preview":0,"Position":2,"SymbolQuality":20,"ResMat":[2,20,5],"Consume":[500001,500],"ResQuality":[2,30],"Reset":[0],"Weight":250},{"ID":1520103,"Name":1520100,"Preview":0,"Position":2,"SymbolQuality":30,"ResMat":[2,30,5],"Consume":[500001,2500],"ResQuality":[2,40],"Reset":[0],"Weight":250},{"ID":1520104,"Name":1520100,"Preview":0,"Position":2,"SymbolQuality":40,"ResMat":[2,40,5],"Consume":[500001,12500],"ResQuality":[2,50],"Reset":[0],"Weight":250},{"ID":1520105,"Name":1520100,"Preview":0,"Position":2,"SymbolQuality":50,"ResMat":[2,50,5],"Consume":[500001,50000],"ResQuality":[2,60],"Reset":[502201,1],"Weight":250},{"ID":1520106,"Name":1520100,"Preview":0,"Position":2,"SymbolQuality":60,"ResMat":[2,60,5],"Consume":[500001,25000],"ResQuality":[2,70],"Reset":[502201,2],"Weight":250},{"ID":1520107,"Name":1520100,"Preview":0,"Position":2,"SymbolQuality":70,"ResMat":[2,70,2],"Consume":[500001,125000],"ResQuality":[2,70],"Reset":[502201,4],"Weight":250},{"ID":1520201,"Name":1520200,"Preview":0,"Position":2,"SymbolQuality":10,"ResMat":[2,10,5],"Consume":[500001,100],"ResQuality":[2,20],"Reset":[0],"Weight":0},{"ID":1520202,"Name":1520200,"Preview":1,"Position":2,"SymbolQuality":20,"ResMat":[2,20,5],"Consume":[500001,500],"ResQuality":[2,30],"Reset":[0],"Weight":250},{"ID":1520203,"Name":1520200,"Preview":0,"Position":2,"SymbolQuality":30,"ResMat":[2,30,5],"Consume":[500001,2500],"ResQuality":[2,40],"Reset":[0],"Weight":250},{"ID":1520204,"Name":1520200,"Preview":0,"Position":2,"SymbolQuality":40,"ResMat":[2,40,5],"Consume":[500001,12500],"ResQuality":[2,50],"Reset":[0],"Weight":250},{"ID":1520205,"Name":1520200,"Preview":0,"Position":2,"SymbolQuality":50,"ResMat":[2,50,5],"Consume":[500001,50000],"ResQuality":[2,60],"Reset":[502201,1],"Weight":250},{"ID":1520206,"Name":1520200,"Preview":0,"Position":2,"SymbolQuality":60,"ResMat":[2,60,5],"Consume":[500001,25000],"ResQuality":[2,70],"Reset":[502201,2],"Weight":250},{"ID":1520207,"Name":1520200,"Preview":0,"Position":2,"SymbolQuality":70,"ResMat":[2,70,2],"Consume":[500001,125000],"ResQuality":[2,70],"Reset":[502201,4],"Weight":250},{"ID":1520301,"Name":1520300,"Preview":1,"Position":2,"SymbolQuality":10,"ResMat":[2,10,5],"Consume":[500001,100],"ResQuality":[2,20],"Reset":[0],"Weight":50},{"ID":1520302,"Name":1520300,"Preview":0,"Position":2,"SymbolQuality":20,"ResMat":[2,20,5],"Consume":[500001,500],"ResQuality":[2,30],"Reset":[0],"Weight":50},{"ID":1520303,"Name":1520300,"Preview":0,"Position":2,"SymbolQuality":30,"ResMat":[2,30,5],"Consume":[500001,2500],"ResQuality":[2,40],"Reset":[0],"Weight":50},{"ID":1520304,"Name":1520300,"Preview":0,"Position":2,"SymbolQuality":40,"ResMat":[2,40,5],"Consume":[500001,12500],"ResQuality":[2,50],"Reset":[0],"Weight":50},{"ID":1520305,"Name":1520300,"Preview":0,"Position":2,"SymbolQuality":50,"ResMat":[2,50,5],"Consume":[500001,50000],"ResQuality":[2,60],"Reset":[502201,1],"Weight":50},{"ID":1520306,"Name":1520300,"Preview":0,"Position":2,"SymbolQuality":60,"ResMat":[2,60,5],"Consume":[500001,25000],"ResQuality":[2,70],"Reset":[502201,2],"Weight":50},{"ID":1520307,"Name":1520300,"Preview":0,"Position":2,"SymbolQuality":70,"ResMat":[2,70,2],"Consume":[500001,125000],"ResQuality":[2,70],"Reset":[502201,4],"Weight":50},{"ID":1520401,"Name":1520400,"Preview":0,"Position":2,"SymbolQuality":10,"ResMat":[2,10,5],"Consume":[500001,100],"ResQuality":[2,20],"Reset":[0],"Weight":0},{"ID":1520402,"Name":1520400,"Preview":1,"Position":2,"SymbolQuality":20,"ResMat":[2,20,5],"Consume":[500001,500],"ResQuality":[2,30],"Reset":[0],"Weight":250},{"ID":1520403,"Name":1520400,"Preview":0,"Position":2,"SymbolQuality":30,"ResMat":[2,30,5],"Consume":[500001,2500],"ResQuality":[2,40],"Reset":[0],"Weight":250},{"ID":1520404,"Name":1520400,"Preview":0,"Position":2,"SymbolQuality":40,"ResMat":[2,40,5],"Consume":[500001,12500],"ResQuality":[2,50],"Reset":[0],"Weight":250},{"ID":1520405,"Name":1520400,"Preview":0,"Position":2,"SymbolQuality":50,"ResMat":[2,50,5],"Consume":[500001,50000],"ResQuality":[2,60],"Reset":[502201,1],"Weight":250},{"ID":1520406,"Name":1520400,"Preview":0,"Position":2,"SymbolQuality":60,"ResMat":[2,60,5],"Consume":[500001,25000],"ResQuality":[2,70],"Reset":[502201,2],"Weight":250},{"ID":1520407,"Name":1520400,"Preview":0,"Position":2,"SymbolQuality":70,"ResMat":[2,70,2],"Consume":[500001,125000],"ResQuality":[2,70],"Reset":[502201,4],"Weight":250},{"ID":1520501,"Name":1520500,"Preview":0,"Position":2,"SymbolQuality":10,"ResMat":[2,10,5],"Consume":[500001,100],"ResQuality":[2,20],"Reset":[0],"Weight":0},{"ID":1520502,"Name":1520500,"Preview":0,"Position":2,"SymbolQuality":20,"ResMat":[2,20,5],"Consume":[500001,500],"ResQuality":[2,30],"Reset":[0],"Weight":0},{"ID":1520503,"Name":1520500,"Preview":1,"Position":2,"SymbolQuality":30,"ResMat":[2,30,5],"Consume":[500001,2500],"ResQuality":[2,40],"Reset":[0],"Weight":250},{"ID":1520504,"Name":1520500,"Preview":0,"Position":2,"SymbolQuality":40,"ResMat":[2,40,5],"Consume":[500001,12500],"ResQuality":[2,50],"Reset":[0],"Weight":250},{"ID":1520505,"Name":1520500,"Preview":0,"Position":2,"SymbolQuality":50,"ResMat":[2,50,5],"Consume":[500001,50000],"ResQuality":[2,60],"Reset":[502201,1],"Weight":250},{"ID":1520506,"Name":1520500,"Preview":0,"Position":2,"SymbolQuality":60,"ResMat":[2,60,5],"Consume":[500001,25000],"ResQuality":[2,70],"Reset":[502201,2],"Weight":250},{"ID":1520507,"Name":1520500,"Preview":0,"Position":2,"SymbolQuality":70,"ResMat":[2,70,2],"Consume":[500001,125000],"ResQuality":[2,70],"Reset":[502201,4],"Weight":250},{"ID":1520601,"Name":1520600,"Preview":0,"Position":2,"SymbolQuality":10,"ResMat":[2,10,5],"Consume":[500001,100],"ResQuality":[2,20],"Reset":[0],"Weight":0},{"ID":1520602,"Name":1520600,"Preview":1,"Position":2,"SymbolQuality":20,"ResMat":[2,20,5],"Consume":[500001,500],"ResQuality":[2,30],"Reset":[0],"Weight":0},{"ID":1520603,"Name":1520600,"Preview":0,"Position":2,"SymbolQuality":30,"ResMat":[2,30,5],"Consume":[500001,2500],"ResQuality":[2,40],"Reset":[0],"Weight":0},{"ID":1520604,"Name":1520600,"Preview":0,"Position":2,"SymbolQuality":40,"ResMat":[2,40,5],"Consume":[500001,12500],"ResQuality":[2,50],"Reset":[0],"Weight":0},{"ID":1520605,"Name":1520600,"Preview":0,"Position":2,"SymbolQuality":50,"ResMat":[2,50,5],"Consume":[500001,50000],"ResQuality":[2,60],"Reset":[502201,1],"Weight":50},{"ID":1520606,"Name":1520600,"Preview":0,"Position":2,"SymbolQuality":60,"ResMat":[2,60,5],"Consume":[500001,25000],"ResQuality":[2,70],"Reset":[502201,2],"Weight":50},{"ID":1520607,"Name":1520600,"Preview":0,"Position":2,"SymbolQuality":70,"ResMat":[2,70,2],"Consume":[500001,125000],"ResQuality":[2,70],"Reset":[502201,4],"Weight":50},{"ID":1520701,"Name":1520700,"Preview":0,"Position":2,"SymbolQuality":10,"ResMat":[2,10,5],"Consume":[500001,100],"ResQuality":[2,20],"Reset":[0],"Weight":0},{"ID":1520702,"Name":1520700,"Preview":0,"Position":2,"SymbolQuality":20,"ResMat":[2,20,5],"Consume":[500001,500],"ResQuality":[2,30],"Reset":[0],"Weight":0},{"ID":1520703,"Name":1520700,"Preview":0,"Position":2,"SymbolQuality":30,"ResMat":[2,30,5],"Consume":[500001,2500],"ResQuality":[2,40],"Reset":[0],"Weight":0},{"ID":1520704,"Name":1520700,"Preview":1,"Position":2,"SymbolQuality":40,"ResMat":[2,40,5],"Consume":[500001,12500],"ResQuality":[2,50],"Reset":[0],"Weight":150},{"ID":1520705,"Name":1520700,"Preview":0,"Position":2,"SymbolQuality":50,"ResMat":[2,50,5],"Consume":[500001,50000],"ResQuality":[2,60],"Reset":[502201,1],"Weight":150},{"ID":1520706,"Name":1520700,"Preview":0,"Position":2,"SymbolQuality":60,"ResMat":[2,60,5],"Consume":[500001,25000],"ResQuality":[2,70],"Reset":[502201,2],"Weight":150},{"ID":1520707,"Name":1520700,"Preview":0,"Position":2,"SymbolQuality":70,"ResMat":[2,70,2],"Consume":[500001,125000],"ResQuality":[2,70],"Reset":[502201,4],"Weight":150},{"ID":1520801,"Name":1520800,"Preview":0,"Position":2,"SymbolQuality":10,"ResMat":[2,10,5],"Consume":[500001,100],"ResQuality":[2,20],"Reset":[0],"Weight":0},{"ID":1520802,"Name":1520800,"Preview":0,"Position":2,"SymbolQuality":20,"ResMat":[2,20,5],"Consume":[500001,500],"ResQuality":[2,30],"Reset":[0],"Weight":0},{"ID":1520803,"Name":1520800,"Preview":1,"Position":2,"SymbolQuality":30,"ResMat":[2,30,5],"Consume":[500001,2500],"ResQuality":[2,40],"Reset":[0],"Weight":150},{"ID":1520804,"Name":1520800,"Preview":0,"Position":2,"SymbolQuality":40,"ResMat":[2,40,5],"Consume":[500001,12500],"ResQuality":[2,50],"Reset":[0],"Weight":150},{"ID":1520805,"Name":1520800,"Preview":0,"Position":2,"SymbolQuality":50,"ResMat":[2,50,5],"Consume":[500001,50000],"ResQuality":[2,60],"Reset":[502201,1],"Weight":150},{"ID":1520806,"Name":1520800,"Preview":0,"Position":2,"SymbolQuality":60,"ResMat":[2,60,5],"Consume":[500001,25000],"ResQuality":[2,70],"Reset":[502201,2],"Weight":150},{"ID":1520807,"Name":1520800,"Preview":0,"Position":2,"SymbolQuality":70,"ResMat":[2,70,2],"Consume":[500001,125000],"ResQuality":[2,70],"Reset":[502201,4],"Weight":150},{"ID":1520901,"Name":1520900,"Preview":0,"Position":2,"SymbolQuality":10,"ResMat":[2,10,5],"Consume":[500001,100],"ResQuality":[2,20],"Reset":[0],"Weight":0},{"ID":1520902,"Name":1520900,"Preview":0,"Position":2,"SymbolQuality":20,"ResMat":[2,20,5],"Consume":[500001,500],"ResQuality":[2,30],"Reset":[0],"Weight":0},{"ID":1520903,"Name":1520900,"Preview":0,"Position":2,"SymbolQuality":30,"ResMat":[2,30,5],"Consume":[500001,2500],"ResQuality":[2,40],"Reset":[0],"Weight":0},{"ID":1520904,"Name":1520900,"Preview":1,"Position":2,"SymbolQuality":40,"ResMat":[2,40,5],"Consume":[500001,12500],"ResQuality":[2,50],"Reset":[0],"Weight":150},{"ID":1520905,"Name":1520900,"Preview":0,"Position":2,"SymbolQuality":50,"ResMat":[2,50,5],"Consume":[500001,50000],"ResQuality":[2,60],"Reset":[502201,1],"Weight":150},{"ID":1520906,"Name":1520900,"Preview":0,"Position":2,"SymbolQuality":60,"ResMat":[2,60,5],"Consume":[500001,25000],"ResQuality":[2,70],"Reset":[502201,2],"Weight":150},{"ID":1520907,"Name":1520900,"Preview":0,"Position":2,"SymbolQuality":70,"ResMat":[2,70,2],"Consume":[500001,125000],"ResQuality":[2,70],"Reset":[502201,4],"Weight":150},{"ID":1521001,"Name":1521000,"Preview":1,"Position":2,"SymbolQuality":10,"ResMat":[2,10,5],"Consume":[500001,100],"ResQuality":[2,20],"Reset":[0],"Weight":50},{"ID":1521002,"Name":1521000,"Preview":0,"Position":2,"SymbolQuality":20,"ResMat":[2,20,5],"Consume":[500001,500],"ResQuality":[2,30],"Reset":[0],"Weight":50},{"ID":1521003,"Name":1521000,"Preview":0,"Position":2,"SymbolQuality":30,"ResMat":[2,30,5],"Consume":[500001,2500],"ResQuality":[2,40],"Reset":[0],"Weight":50},{"ID":1521004,"Name":1521000,"Preview":0,"Position":2,"SymbolQuality":40,"ResMat":[2,40,5],"Consume":[500001,12500],"ResQuality":[2,50],"Reset":[0],"Weight":50},{"ID":1521005,"Name":1521000,"Preview":0,"Position":2,"SymbolQuality":50,"ResMat":[2,50,5],"Consume":[500001,50000],"ResQuality":[2,60],"Reset":[502201,1],"Weight":50},{"ID":1521006,"Name":1521000,"Preview":0,"Position":2,"SymbolQuality":60,"ResMat":[2,60,5],"Consume":[500001,25000],"ResQuality":[2,70],"Reset":[502201,2],"Weight":50},{"ID":1521007,"Name":1521000,"Preview":0,"Position":2,"SymbolQuality":70,"ResMat":[2,70,2],"Consume":[500001,125000],"ResQuality":[2,70],"Reset":[502201,4],"Weight":50},{"ID":1521101,"Name":1521100,"Preview":1,"Position":2,"SymbolQuality":10,"ResMat":[2,10,5],"Consume":[500001,100],"ResQuality":[2,20],"Reset":[0],"Weight":50},{"ID":1521102,"Name":1521100,"Preview":0,"Position":2,"SymbolQuality":20,"ResMat":[2,20,5],"Consume":[500001,500],"ResQuality":[2,30],"Reset":[0],"Weight":50},{"ID":1521103,"Name":1521100,"Preview":0,"Position":2,"SymbolQuality":30,"ResMat":[2,30,5],"Consume":[500001,2500],"ResQuality":[2,40],"Reset":[0],"Weight":50},{"ID":1521104,"Name":1521100,"Preview":0,"Position":2,"SymbolQuality":40,"ResMat":[2,40,5],"Consume":[500001,12500],"ResQuality":[2,50],"Reset":[0],"Weight":50},{"ID":1521105,"Name":1521100,"Preview":0,"Position":2,"SymbolQuality":50,"ResMat":[2,50,5],"Consume":[500001,50000],"ResQuality":[2,60],"Reset":[502201,1],"Weight":50},{"ID":1521106,"Name":1521100,"Preview":0,"Position":2,"SymbolQuality":60,"ResMat":[2,60,5],"Consume":[500001,25000],"ResQuality":[2,70],"Reset":[502201,2],"Weight":50},{"ID":1521107,"Name":1521100,"Preview":0,"Position":2,"SymbolQuality":70,"ResMat":[2,70,2],"Consume":[500001,125000],"ResQuality":[2,70],"Reset":[502201,4],"Weight":50},{"ID":1521201,"Name":1521200,"Preview":1,"Position":2,"SymbolQuality":10,"ResMat":[2,10,5],"Consume":[500001,100],"ResQuality":[2,20],"Reset":[0],"Weight":50},{"ID":1521202,"Name":1521200,"Preview":0,"Position":2,"SymbolQuality":20,"ResMat":[2,20,5],"Consume":[500001,500],"ResQuality":[2,30],"Reset":[0],"Weight":50},{"ID":1521203,"Name":1521200,"Preview":0,"Position":2,"SymbolQuality":30,"ResMat":[2,30,5],"Consume":[500001,2500],"ResQuality":[2,40],"Reset":[0],"Weight":50},{"ID":1521204,"Name":1521200,"Preview":0,"Position":2,"SymbolQuality":40,"ResMat":[2,40,5],"Consume":[500001,12500],"ResQuality":[2,50],"Reset":[0],"Weight":50},{"ID":1521205,"Name":1521200,"Preview":0,"Position":2,"SymbolQuality":50,"ResMat":[2,50,5],"Consume":[500001,50000],"ResQuality":[2,60],"Reset":[502201,1],"Weight":50},{"ID":1521206,"Name":1521200,"Preview":0,"Position":2,"SymbolQuality":60,"ResMat":[2,60,5],"Consume":[500001,25000],"ResQuality":[2,70],"Reset":[502201,2],"Weight":50},{"ID":1521207,"Name":1521200,"Preview":0,"Position":2,"SymbolQuality":70,"ResMat":[2,70,2],"Consume":[500001,125000],"ResQuality":[2,70],"Reset":[502201,4],"Weight":50},{"ID":1530101,"Name":1530100,"Preview":0,"Position":3,"SymbolQuality":10,"ResMat":[3,10,5],"Consume":[500001,100],"ResQuality":[3,20],"Reset":[0],"Weight":0},{"ID":1530102,"Name":1530100,"Preview":0,"Position":3,"SymbolQuality":20,"ResMat":[3,20,5],"Consume":[500001,500],"ResQuality":[3,30],"Reset":[0],"Weight":0},{"ID":1530103,"Name":1530100,"Preview":0,"Position":3,"SymbolQuality":30,"ResMat":[3,30,5],"Consume":[500001,2500],"ResQuality":[3,40],"Reset":[0],"Weight":0},{"ID":1530104,"Name":1530100,"Preview":0,"Position":3,"SymbolQuality":40,"ResMat":[3,40,5],"Consume":[500001,12500],"ResQuality":[3,50],"Reset":[0],"Weight":0},{"ID":1530105,"Name":1530100,"Preview":1,"Position":3,"SymbolQuality":50,"ResMat":[3,50,5],"Consume":[500001,50000],"ResQuality":[3,60],"Reset":[502201,1],"Weight":50},{"ID":1530106,"Name":1530100,"Preview":0,"Position":3,"SymbolQuality":60,"ResMat":[3,60,5],"Consume":[500001,25000],"ResQuality":[3,70],"Reset":[502201,2],"Weight":50},{"ID":1530107,"Name":1530100,"Preview":0,"Position":3,"SymbolQuality":70,"ResMat":[3,70,2],"Consume":[500001,125000],"ResQuality":[3,70],"Reset":[502201,4],"Weight":50},{"ID":1530201,"Name":1530200,"Preview":1,"Position":3,"SymbolQuality":10,"ResMat":[3,10,5],"Consume":[500001,100],"ResQuality":[3,20],"Reset":[0],"Weight":250},{"ID":1530202,"Name":1530200,"Preview":0,"Position":3,"SymbolQuality":20,"ResMat":[3,20,5],"Consume":[500001,500],"ResQuality":[3,30],"Reset":[0],"Weight":250},{"ID":1530203,"Name":1530200,"Preview":0,"Position":3,"SymbolQuality":30,"ResMat":[3,30,5],"Consume":[500001,2500],"ResQuality":[3,40],"Reset":[0],"Weight":250},{"ID":1530204,"Name":1530200,"Preview":0,"Position":3,"SymbolQuality":40,"ResMat":[3,40,5],"Consume":[500001,12500],"ResQuality":[3,50],"Reset":[0],"Weight":250},{"ID":1530205,"Name":1530200,"Preview":0,"Position":3,"SymbolQuality":50,"ResMat":[3,50,5],"Consume":[500001,50000],"ResQuality":[3,60],"Reset":[502201,1],"Weight":250},{"ID":1530206,"Name":1530200,"Preview":0,"Position":3,"SymbolQuality":60,"ResMat":[3,60,5],"Consume":[500001,25000],"ResQuality":[3,70],"Reset":[502201,2],"Weight":250},{"ID":1530207,"Name":1530200,"Preview":0,"Position":3,"SymbolQuality":70,"ResMat":[3,70,2],"Consume":[500001,125000],"ResQuality":[3,70],"Reset":[502201,4],"Weight":250},{"ID":1530301,"Name":1530300,"Preview":0,"Position":3,"SymbolQuality":10,"ResMat":[3,10,5],"Consume":[500001,100],"ResQuality":[3,20],"Reset":[0],"Weight":0},{"ID":1530302,"Name":1530300,"Preview":0,"Position":3,"SymbolQuality":20,"ResMat":[3,20,5],"Consume":[500001,500],"ResQuality":[3,30],"Reset":[0],"Weight":0},{"ID":1530303,"Name":1530300,"Preview":1,"Position":3,"SymbolQuality":30,"ResMat":[3,30,5],"Consume":[500001,2500],"ResQuality":[3,40],"Reset":[0],"Weight":150},{"ID":1530304,"Name":1530300,"Preview":0,"Position":3,"SymbolQuality":40,"ResMat":[3,40,5],"Consume":[500001,12500],"ResQuality":[3,50],"Reset":[0],"Weight":150},{"ID":1530305,"Name":1530300,"Preview":0,"Position":3,"SymbolQuality":50,"ResMat":[3,50,5],"Consume":[500001,50000],"ResQuality":[3,60],"Reset":[502201,1],"Weight":150},{"ID":1530306,"Name":1530300,"Preview":0,"Position":3,"SymbolQuality":60,"ResMat":[3,60,5],"Consume":[500001,25000],"ResQuality":[3,70],"Reset":[502201,2],"Weight":150},{"ID":1530307,"Name":1530300,"Preview":0,"Position":3,"SymbolQuality":70,"ResMat":[3,70,2],"Consume":[500001,125000],"ResQuality":[3,70],"Reset":[502201,4],"Weight":150},{"ID":1530401,"Name":1530400,"Preview":0,"Position":3,"SymbolQuality":10,"ResMat":[3,10,5],"Consume":[500001,100],"ResQuality":[3,20],"Reset":[0],"Weight":0},{"ID":1530402,"Name":1530400,"Preview":1,"Position":3,"SymbolQuality":20,"ResMat":[3,20,5],"Consume":[500001,500],"ResQuality":[3,30],"Reset":[0],"Weight":150},{"ID":1530403,"Name":1530400,"Preview":0,"Position":3,"SymbolQuality":30,"ResMat":[3,30,5],"Consume":[500001,2500],"ResQuality":[3,40],"Reset":[0],"Weight":150},{"ID":1530404,"Name":1530400,"Preview":0,"Position":3,"SymbolQuality":40,"ResMat":[3,40,5],"Consume":[500001,12500],"ResQuality":[3,50],"Reset":[0],"Weight":150},{"ID":1530405,"Name":1530400,"Preview":0,"Position":3,"SymbolQuality":50,"ResMat":[3,50,5],"Consume":[500001,50000],"ResQuality":[3,60],"Reset":[502201,1],"Weight":150},{"ID":1530406,"Name":1530400,"Preview":0,"Position":3,"SymbolQuality":60,"ResMat":[3,60,5],"Consume":[500001,25000],"ResQuality":[3,70],"Reset":[502201,2],"Weight":150},{"ID":1530407,"Name":1530400,"Preview":0,"Position":3,"SymbolQuality":70,"ResMat":[3,70,2],"Consume":[500001,125000],"ResQuality":[3,70],"Reset":[502201,4],"Weight":150},{"ID":1530501,"Name":1530500,"Preview":0,"Position":3,"SymbolQuality":10,"ResMat":[3,10,5],"Consume":[500001,100],"ResQuality":[3,20],"Reset":[0],"Weight":0},{"ID":1530502,"Name":1530500,"Preview":1,"Position":3,"SymbolQuality":20,"ResMat":[3,20,5],"Consume":[500001,500],"ResQuality":[3,30],"Reset":[0],"Weight":150},{"ID":1530503,"Name":1530500,"Preview":0,"Position":3,"SymbolQuality":30,"ResMat":[3,30,5],"Consume":[500001,2500],"ResQuality":[3,40],"Reset":[0],"Weight":150},{"ID":1530504,"Name":1530500,"Preview":0,"Position":3,"SymbolQuality":40,"ResMat":[3,40,5],"Consume":[500001,12500],"ResQuality":[3,50],"Reset":[0],"Weight":150},{"ID":1530505,"Name":1530500,"Preview":0,"Position":3,"SymbolQuality":50,"ResMat":[3,50,5],"Consume":[500001,50000],"ResQuality":[3,60],"Reset":[502201,1],"Weight":150},{"ID":1530506,"Name":1530500,"Preview":0,"Position":3,"SymbolQuality":60,"ResMat":[3,60,5],"Consume":[500001,25000],"ResQuality":[3,70],"Reset":[502201,2],"Weight":150},{"ID":1530507,"Name":1530500,"Preview":0,"Position":3,"SymbolQuality":70,"ResMat":[3,70,2],"Consume":[500001,125000],"ResQuality":[3,70],"Reset":[502201,4],"Weight":150},{"ID":1530601,"Name":1530600,"Preview":0,"Position":3,"SymbolQuality":10,"ResMat":[3,10,5],"Consume":[500001,100],"ResQuality":[3,20],"Reset":[0],"Weight":0},{"ID":1530602,"Name":1530600,"Preview":0,"Position":3,"SymbolQuality":20,"ResMat":[3,20,5],"Consume":[500001,500],"ResQuality":[3,30],"Reset":[0],"Weight":0},{"ID":1530603,"Name":1530600,"Preview":0,"Position":3,"SymbolQuality":30,"ResMat":[3,30,5],"Consume":[500001,2500],"ResQuality":[3,40],"Reset":[0],"Weight":0},{"ID":1530604,"Name":1530600,"Preview":1,"Position":3,"SymbolQuality":40,"ResMat":[3,40,5],"Consume":[500001,12500],"ResQuality":[3,50],"Reset":[0],"Weight":50},{"ID":1530605,"Name":1530600,"Preview":0,"Position":3,"SymbolQuality":50,"ResMat":[3,50,5],"Consume":[500001,50000],"ResQuality":[3,60],"Reset":[502201,1],"Weight":50},{"ID":1530606,"Name":1530600,"Preview":0,"Position":3,"SymbolQuality":60,"ResMat":[3,60,5],"Consume":[500001,25000],"ResQuality":[3,70],"Reset":[502201,2],"Weight":50},{"ID":1530607,"Name":1530600,"Preview":0,"Position":3,"SymbolQuality":70,"ResMat":[3,70,2],"Consume":[500001,125000],"ResQuality":[3,70],"Reset":[502201,4],"Weight":50},{"ID":1530701,"Name":1530700,"Preview":0,"Position":3,"SymbolQuality":10,"ResMat":[3,10,5],"Consume":[500001,100],"ResQuality":[3,20],"Reset":[0],"Weight":0},{"ID":1530702,"Name":1530700,"Preview":0,"Position":3,"SymbolQuality":20,"ResMat":[3,20,5],"Consume":[500001,500],"ResQuality":[3,30],"Reset":[0],"Weight":0},{"ID":1530703,"Name":1530700,"Preview":0,"Position":3,"SymbolQuality":30,"ResMat":[3,30,5],"Consume":[500001,2500],"ResQuality":[3,40],"Reset":[0],"Weight":0},{"ID":1530704,"Name":1530700,"Preview":1,"Position":3,"SymbolQuality":40,"ResMat":[3,40,5],"Consume":[500001,12500],"ResQuality":[3,50],"Reset":[0],"Weight":50},{"ID":1530705,"Name":1530700,"Preview":0,"Position":3,"SymbolQuality":50,"ResMat":[3,50,5],"Consume":[500001,50000],"ResQuality":[3,60],"Reset":[502201,1],"Weight":50},{"ID":1530706,"Name":1530700,"Preview":0,"Position":3,"SymbolQuality":60,"ResMat":[3,60,5],"Consume":[500001,25000],"ResQuality":[3,70],"Reset":[502201,2],"Weight":50},{"ID":1530707,"Name":1530700,"Preview":0,"Position":3,"SymbolQuality":70,"ResMat":[3,70,2],"Consume":[500001,125000],"ResQuality":[3,70],"Reset":[502201,4],"Weight":50},{"ID":1530801,"Name":1530800,"Preview":1,"Position":3,"SymbolQuality":10,"ResMat":[3,10,5],"Consume":[500001,100],"ResQuality":[3,20],"Reset":[0],"Weight":150},{"ID":1530802,"Name":1530800,"Preview":0,"Position":3,"SymbolQuality":20,"ResMat":[3,20,5],"Consume":[500001,500],"ResQuality":[3,30],"Reset":[0],"Weight":150},{"ID":1530803,"Name":1530800,"Preview":0,"Position":3,"SymbolQuality":30,"ResMat":[3,30,5],"Consume":[500001,2500],"ResQuality":[3,40],"Reset":[0],"Weight":150},{"ID":1530804,"Name":1530800,"Preview":0,"Position":3,"SymbolQuality":40,"ResMat":[3,40,5],"Consume":[500001,12500],"ResQuality":[3,50],"Reset":[0],"Weight":150},{"ID":1530805,"Name":1530800,"Preview":0,"Position":3,"SymbolQuality":50,"ResMat":[3,50,5],"Consume":[500001,50000],"ResQuality":[3,60],"Reset":[502201,1],"Weight":150},{"ID":1530806,"Name":1530800,"Preview":0,"Position":3,"SymbolQuality":60,"ResMat":[3,60,5],"Consume":[500001,25000],"ResQuality":[3,70],"Reset":[502201,2],"Weight":150},{"ID":1530807,"Name":1530800,"Preview":0,"Position":3,"SymbolQuality":70,"ResMat":[3,70,2],"Consume":[500001,125000],"ResQuality":[3,70],"Reset":[502201,4],"Weight":150},{"ID":1530901,"Name":1530900,"Preview":1,"Position":3,"SymbolQuality":10,"ResMat":[3,10,5],"Consume":[500001,100],"ResQuality":[3,20],"Reset":[0],"Weight":150},{"ID":1530902,"Name":1530900,"Preview":0,"Position":3,"SymbolQuality":20,"ResMat":[3,20,5],"Consume":[500001,500],"ResQuality":[3,30],"Reset":[0],"Weight":150},{"ID":1530903,"Name":1530900,"Preview":0,"Position":3,"SymbolQuality":30,"ResMat":[3,30,5],"Consume":[500001,2500],"ResQuality":[3,40],"Reset":[0],"Weight":150},{"ID":1530904,"Name":1530900,"Preview":0,"Position":3,"SymbolQuality":40,"ResMat":[3,40,5],"Consume":[500001,12500],"ResQuality":[3,50],"Reset":[0],"Weight":150},{"ID":1530905,"Name":1530900,"Preview":0,"Position":3,"SymbolQuality":50,"ResMat":[3,50,5],"Consume":[500001,50000],"ResQuality":[3,60],"Reset":[502201,1],"Weight":150},{"ID":1530906,"Name":1530900,"Preview":0,"Position":3,"SymbolQuality":60,"ResMat":[3,60,5],"Consume":[500001,25000],"ResQuality":[3,70],"Reset":[502201,2],"Weight":150},{"ID":1530907,"Name":1530900,"Preview":0,"Position":3,"SymbolQuality":70,"ResMat":[3,70,2],"Consume":[500001,125000],"ResQuality":[3,70],"Reset":[502201,4],"Weight":150},{"ID":1540101,"Name":1540100,"Preview":0,"Position":4,"SymbolQuality":10,"ResMat":[4,10,5],"Consume":[500001,100],"ResQuality":[4,20],"Reset":[0],"Weight":0},{"ID":1540102,"Name":1540100,"Preview":0,"Position":4,"SymbolQuality":20,"ResMat":[4,20,5],"Consume":[500001,500],"ResQuality":[4,30],"Reset":[0],"Weight":0},{"ID":1540103,"Name":1540100,"Preview":0,"Position":4,"SymbolQuality":30,"ResMat":[4,30,5],"Consume":[500001,2500],"ResQuality":[4,40],"Reset":[0],"Weight":0},{"ID":1540104,"Name":1540100,"Preview":1,"Position":4,"SymbolQuality":40,"ResMat":[4,40,5],"Consume":[500001,12500],"ResQuality":[4,50],"Reset":[0],"Weight":50},{"ID":1540105,"Name":1540100,"Preview":0,"Position":4,"SymbolQuality":50,"ResMat":[4,50,5],"Consume":[500001,50000],"ResQuality":[4,60],"Reset":[502201,1],"Weight":50},{"ID":1540106,"Name":1540100,"Preview":0,"Position":4,"SymbolQuality":60,"ResMat":[4,60,5],"Consume":[500001,25000],"ResQuality":[4,70],"Reset":[502201,2],"Weight":50},{"ID":1540107,"Name":1540100,"Preview":0,"Position":4,"SymbolQuality":70,"ResMat":[4,70,2],"Consume":[500001,125000],"ResQuality":[4,70],"Reset":[502201,4],"Weight":50},{"ID":1540201,"Name":1540200,"Preview":0,"Position":4,"SymbolQuality":10,"ResMat":[4,10,5],"Consume":[500001,100],"ResQuality":[4,20],"Reset":[0],"Weight":0},{"ID":1540202,"Name":1540200,"Preview":1,"Position":4,"SymbolQuality":20,"ResMat":[4,20,5],"Consume":[500001,500],"ResQuality":[4,30],"Reset":[0],"Weight":150},{"ID":1540203,"Name":1540200,"Preview":0,"Position":4,"SymbolQuality":30,"ResMat":[4,30,5],"Consume":[500001,2500],"ResQuality":[4,40],"Reset":[0],"Weight":150},{"ID":1540204,"Name":1540200,"Preview":0,"Position":4,"SymbolQuality":40,"ResMat":[4,40,5],"Consume":[500001,12500],"ResQuality":[4,50],"Reset":[0],"Weight":150},{"ID":1540205,"Name":1540200,"Preview":0,"Position":4,"SymbolQuality":50,"ResMat":[4,50,5],"Consume":[500001,50000],"ResQuality":[4,60],"Reset":[502201,1],"Weight":150},{"ID":1540206,"Name":1540200,"Preview":0,"Position":4,"SymbolQuality":60,"ResMat":[4,60,5],"Consume":[500001,25000],"ResQuality":[4,70],"Reset":[502201,2],"Weight":150},{"ID":1540207,"Name":1540200,"Preview":0,"Position":4,"SymbolQuality":70,"ResMat":[4,70,2],"Consume":[500001,125000],"ResQuality":[4,70],"Reset":[502201,4],"Weight":150},{"ID":1540301,"Name":1540300,"Preview":0,"Position":4,"SymbolQuality":10,"ResMat":[4,10,5],"Consume":[500001,100],"ResQuality":[4,20],"Reset":[0],"Weight":0},{"ID":1540302,"Name":1540300,"Preview":0,"Position":4,"SymbolQuality":20,"ResMat":[4,20,5],"Consume":[500001,500],"ResQuality":[4,30],"Reset":[0],"Weight":0},{"ID":1540303,"Name":1540300,"Preview":0,"Position":4,"SymbolQuality":30,"ResMat":[4,30,5],"Consume":[500001,2500],"ResQuality":[4,40],"Reset":[0],"Weight":0},{"ID":1540304,"Name":1540300,"Preview":1,"Position":4,"SymbolQuality":40,"ResMat":[4,40,5],"Consume":[500001,12500],"ResQuality":[4,50],"Reset":[0],"Weight":150},{"ID":1540305,"Name":1540300,"Preview":0,"Position":4,"SymbolQuality":50,"ResMat":[4,50,5],"Consume":[500001,50000],"ResQuality":[4,60],"Reset":[502201,1],"Weight":150},{"ID":1540306,"Name":1540300,"Preview":0,"Position":4,"SymbolQuality":60,"ResMat":[4,60,5],"Consume":[500001,25000],"ResQuality":[4,70],"Reset":[502201,2],"Weight":150},{"ID":1540307,"Name":1540300,"Preview":0,"Position":4,"SymbolQuality":70,"ResMat":[4,70,2],"Consume":[500001,125000],"ResQuality":[4,70],"Reset":[502201,4],"Weight":150},{"ID":1540401,"Name":1540400,"Preview":1,"Position":4,"SymbolQuality":10,"ResMat":[4,10,5],"Consume":[500001,100],"ResQuality":[4,20],"Reset":[0],"Weight":150},{"ID":1540402,"Name":1540400,"Preview":0,"Position":4,"SymbolQuality":20,"ResMat":[4,20,5],"Consume":[500001,500],"ResQuality":[4,30],"Reset":[0],"Weight":150},{"ID":1540403,"Name":1540400,"Preview":0,"Position":4,"SymbolQuality":30,"ResMat":[4,30,5],"Consume":[500001,2500],"ResQuality":[4,40],"Reset":[0],"Weight":150},{"ID":1540404,"Name":1540400,"Preview":0,"Position":4,"SymbolQuality":40,"ResMat":[4,40,5],"Consume":[500001,12500],"ResQuality":[4,50],"Reset":[0],"Weight":150},{"ID":1540405,"Name":1540400,"Preview":0,"Position":4,"SymbolQuality":50,"ResMat":[4,50,5],"Consume":[500001,50000],"ResQuality":[4,60],"Reset":[502201,1],"Weight":150},{"ID":1540406,"Name":1540400,"Preview":0,"Position":4,"SymbolQuality":60,"ResMat":[4,60,5],"Consume":[500001,25000],"ResQuality":[4,70],"Reset":[502201,2],"Weight":150},{"ID":1540407,"Name":1540400,"Preview":0,"Position":4,"SymbolQuality":70,"ResMat":[4,70,2],"Consume":[500001,125000],"ResQuality":[4,70],"Reset":[502201,4],"Weight":150},{"ID":1540501,"Name":1540500,"Preview":0,"Position":4,"SymbolQuality":10,"ResMat":[4,10,5],"Consume":[500001,100],"ResQuality":[4,20],"Reset":[0],"Weight":0},{"ID":1540502,"Name":1540500,"Preview":0,"Position":4,"SymbolQuality":20,"ResMat":[4,20,5],"Consume":[500001,500],"ResQuality":[4,30],"Reset":[0],"Weight":0},{"ID":1540503,"Name":1540500,"Preview":0,"Position":4,"SymbolQuality":30,"ResMat":[4,30,5],"Consume":[500001,2500],"ResQuality":[4,40],"Reset":[0],"Weight":0},{"ID":1540504,"Name":1540500,"Preview":0,"Position":4,"SymbolQuality":40,"ResMat":[4,40,5],"Consume":[500001,12500],"ResQuality":[4,50],"Reset":[0],"Weight":0},{"ID":1540505,"Name":1540500,"Preview":1,"Position":4,"SymbolQuality":50,"ResMat":[4,50,5],"Consume":[500001,50000],"ResQuality":[4,60],"Reset":[502201,1],"Weight":50},{"ID":1540506,"Name":1540500,"Preview":0,"Position":4,"SymbolQuality":60,"ResMat":[4,60,5],"Consume":[500001,25000],"ResQuality":[4,70],"Reset":[502201,2],"Weight":50},{"ID":1540507,"Name":1540500,"Preview":0,"Position":4,"SymbolQuality":70,"ResMat":[4,70,2],"Consume":[500001,125000],"ResQuality":[4,70],"Reset":[502201,4],"Weight":50},{"ID":1540601,"Name":1540600,"Preview":0,"Position":4,"SymbolQuality":10,"ResMat":[4,10,5],"Consume":[500001,100],"ResQuality":[4,20],"Reset":[0],"Weight":0},{"ID":1540602,"Name":1540600,"Preview":0,"Position":4,"SymbolQuality":20,"ResMat":[4,20,5],"Consume":[500001,500],"ResQuality":[4,30],"Reset":[0],"Weight":0},{"ID":1540603,"Name":1540600,"Preview":1,"Position":4,"SymbolQuality":30,"ResMat":[4,30,5],"Consume":[500001,2500],"ResQuality":[4,40],"Reset":[0],"Weight":50},{"ID":1540604,"Name":1540600,"Preview":0,"Position":4,"SymbolQuality":40,"ResMat":[4,40,5],"Consume":[500001,12500],"ResQuality":[4,50],"Reset":[0],"Weight":50},{"ID":1540605,"Name":1540600,"Preview":0,"Position":4,"SymbolQuality":50,"ResMat":[4,50,5],"Consume":[500001,50000],"ResQuality":[4,60],"Reset":[502201,1],"Weight":50},{"ID":1540606,"Name":1540600,"Preview":0,"Position":4,"SymbolQuality":60,"ResMat":[4,60,5],"Consume":[500001,25000],"ResQuality":[4,70],"Reset":[502201,2],"Weight":50},{"ID":1540607,"Name":1540600,"Preview":0,"Position":4,"SymbolQuality":70,"ResMat":[4,70,2],"Consume":[500001,125000],"ResQuality":[4,70],"Reset":[502201,4],"Weight":50},{"ID":1540701,"Name":1540700,"Preview":0,"Position":4,"SymbolQuality":10,"ResMat":[4,10,5],"Consume":[500001,100],"ResQuality":[4,20],"Reset":[0],"Weight":0},{"ID":1540702,"Name":1540700,"Preview":1,"Position":4,"SymbolQuality":20,"ResMat":[4,20,5],"Consume":[500001,500],"ResQuality":[4,30],"Reset":[0],"Weight":250},{"ID":1540703,"Name":1540700,"Preview":0,"Position":4,"SymbolQuality":30,"ResMat":[4,30,5],"Consume":[500001,2500],"ResQuality":[4,40],"Reset":[0],"Weight":250},{"ID":1540704,"Name":1540700,"Preview":0,"Position":4,"SymbolQuality":40,"ResMat":[4,40,5],"Consume":[500001,12500],"ResQuality":[4,50],"Reset":[0],"Weight":250},{"ID":1540705,"Name":1540700,"Preview":0,"Position":4,"SymbolQuality":50,"ResMat":[4,50,5],"Consume":[500001,50000],"ResQuality":[4,60],"Reset":[502201,1],"Weight":250},{"ID":1540706,"Name":1540700,"Preview":0,"Position":4,"SymbolQuality":60,"ResMat":[4,60,5],"Consume":[500001,25000],"ResQuality":[4,70],"Reset":[502201,2],"Weight":250},{"ID":1540707,"Name":1540700,"Preview":0,"Position":4,"SymbolQuality":70,"ResMat":[4,70,2],"Consume":[500001,125000],"ResQuality":[4,70],"Reset":[502201,4],"Weight":250},{"ID":1540801,"Name":1540800,"Preview":1,"Position":4,"SymbolQuality":10,"ResMat":[4,10,5],"Consume":[500001,100],"ResQuality":[4,20],"Reset":[0],"Weight":250},{"ID":1540802,"Name":1540800,"Preview":0,"Position":4,"SymbolQuality":20,"ResMat":[4,20,5],"Consume":[500001,500],"ResQuality":[4,30],"Reset":[0],"Weight":250},{"ID":1540803,"Name":1540800,"Preview":0,"Position":4,"SymbolQuality":30,"ResMat":[4,30,5],"Consume":[500001,2500],"ResQuality":[4,40],"Reset":[0],"Weight":250},{"ID":1540804,"Name":1540800,"Preview":0,"Position":4,"SymbolQuality":40,"ResMat":[4,40,5],"Consume":[500001,12500],"ResQuality":[4,50],"Reset":[0],"Weight":250},{"ID":1540805,"Name":1540800,"Preview":0,"Position":4,"SymbolQuality":50,"ResMat":[4,50,5],"Consume":[500001,50000],"ResQuality":[4,60],"Reset":[502201,1],"Weight":250},{"ID":1540806,"Name":1540800,"Preview":0,"Position":4,"SymbolQuality":60,"ResMat":[4,60,5],"Consume":[500001,25000],"ResQuality":[4,70],"Reset":[502201,2],"Weight":250},{"ID":1540807,"Name":1540800,"Preview":0,"Position":4,"SymbolQuality":70,"ResMat":[4,70,2],"Consume":[500001,125000],"ResQuality":[4,70],"Reset":[502201,4],"Weight":250}]